chat_test.py
mcp_m365_mgmt.py
test_client.py
mcp_m365_mgmt-1.0.2.dist-info/licenses/LICENSE
mcp_m365_mgmt-1.0.2.dist-info/METADATA
mcp_m365_mgmt-1.0.2.dist-info/WHEEL
mcp_m365_mgmt-1.0.2.dist-info/entry_points.txt
mcp_m365_mgmt-1.0.2.dist-info/top_level.txt
mcp_m365_mgmt-1.0.2.dist-info/RECORD
