Metadata-Version: 2.4
Name: mcp-m365-mgmt
Version: 1.0.2
Summary: MCP server for Microsoft 365 and Intune management with 33 tools for Entra ID, devices, Autopilot, and more
Home-page: https://github.com/thiagogbeier/mcp-m365-mgmt
Author: Thiago Beier
Author-email: Thiago Beier <thiago.beier@gmail.com>
Maintainer-email: Thiago Beier <thiago.beier@gmail.com>
License: MIT
Project-URL: Homepage, https://github.com/thiagogbeier/mcp-m365-mgmt
Project-URL: Repository, https://github.com/thiagogbeier/mcp-m365-mgmt
Project-URL: Issues, https://github.com/thiagogbeier/mcp-m365-mgmt/issues
Project-URL: Documentation, https://github.com/thiagogbeier/mcp-m365-mgmt#readme
Project-URL: Changelog, https://github.com/thiagogbeier/mcp-m365-mgmt/blob/main/CHANGELOG.md
Keywords: mcp,microsoft-365,intune,entra-id,azure-ad,autopilot,device-management,sharepoint,graph-api,model-context-protocol
Classifier: Development Status :: 5 - Production/Stable
Classifier: Intended Audience :: Developers
Classifier: Intended Audience :: System Administrators
Classifier: License :: OSI Approved :: MIT License
Classifier: Operating System :: OS Independent
Classifier: Programming Language :: Python :: 3
Classifier: Programming Language :: Python :: 3.9
Classifier: Programming Language :: Python :: 3.10
Classifier: Programming Language :: Python :: 3.11
Classifier: Programming Language :: Python :: 3.12
Classifier: Programming Language :: Python :: 3.13
Classifier: Topic :: Software Development :: Libraries :: Python Modules
Classifier: Topic :: System :: Systems Administration
Classifier: Topic :: Office/Business
Requires-Python: >=3.9
License-File: LICENSE
Requires-Dist: fastmcp>=0.1.0
Requires-Dist: azure-identity>=1.25.0
Requires-Dist: requests>=2.31.0
Requires-Dist: python-docx>=1.1.0
Requires-Dist: openpyxl>=3.1.0
Requires-Dist: python-pptx>=0.6.23
Requires-Dist: odfpy>=1.4.1
Requires-Dist: python-dotenv>=1.0.0
Provides-Extra: dev
Requires-Dist: build>=0.10.0; extra == "dev"
Requires-Dist: twine>=4.0.0; extra == "dev"
Requires-Dist: pytest>=7.0.0; extra == "dev"
Dynamic: author
Dynamic: home-page
Dynamic: license-file
Dynamic: requires-python
